{
    "version": 1,
    "info": {
        "title": "Hilbert Transfrom",
        "author": "David Schwarz",
        "description": "Applies HHT to a signal",
        "name": "HHT",
        "cppType": "custom_block",
        "preferConvolution": false,
        "visualization": "dimensionalityReduction",
        "experimental": false,
        "latestImplementationVersion": 1
    },
    "parameters": [
        {
            "group": "Scaling",
            "items": [
                {
                    "name": "Scale axes",
                    "value": 1,
                    "type": "float",
                    "help": "Multiplies axes by this number",
                    "param": "scale-axes"
                }
            ],
            "group": "Filter",
            "items": [
                {
                    "name": "HHT length",
                    "value": 256,
                    "type": "int",
                    "help": "number of HHT points",
                    "param": "hht_len"
                }
            ]
        }
    ]
}
